cropmirror_utils-0.0.2.dist-info/licenses/LICENSE
example/__init__.py
example/say.py
cropmirror_utils-0.0.2.dist-info/METADATA
cropmirror_utils-0.0.2.dist-info/WHEEL
cropmirror_utils-0.0.2.dist-info/top_level.txt
cropmirror_utils-0.0.2.dist-info/RECORD
