Metadata-Version: 2.4
Name: cropmirror_utils
Version: 0.0.2
Summary: 云稷基础算法库
Author: Long.liu, Wenchang
License: MIT License
Classifier: Programming Language :: Python :: 3
Classifier: Operating System :: OS Independent
Classifier: License :: OSI Approved :: MIT License
Requires-Python: >=3.6
License-File: LICENSE
Dynamic: license-file
